fijiconvert/__init__.py
fijiconvert/buildsetup.py
fijiconvert/converter.py
fijiconvert/main.py
fijiconvert/reader.py
fijiconvert/setupcheckerr.py
fijiconvert/tacchkdlg.py
fijiconvert/ui_fijiconvertdialog.py
fijiconvert/writer.py
fijiconvert/xml_gui.py
fijiconvert-1.0.2.dist-info/METADATA
fijiconvert-1.0.2.dist-info/WHEEL
fijiconvert-1.0.2.dist-info/entry_points.txt
fijiconvert-1.0.2.dist-info/top_level.txt
fijiconvert-1.0.2.dist-info/RECORD
