Metadata-Version: 2.1
Name: fijiconvert
Version: 1.0.2
Summary: For converting FIJI markers and regions to XML
Home-page: https://pypi.org/project/fijiconvert/
Author: Jean Fecteau
Author-email: jfecteau@mbfbioscience.com
Keywords: sparc,mbf,bioscience,fiji,xml
Requires-Python: >=3.6
Requires-Dist: PyQt5
